adafruit_vl53l1x.py
adafruit_circuitpython_vl53l1x-1.2.6.dist-info/licenses/LICENSE
adafruit_circuitpython_vl53l1x-1.2.6.dist-info/METADATA
adafruit_circuitpython_vl53l1x-1.2.6.dist-info/WHEEL
adafruit_circuitpython_vl53l1x-1.2.6.dist-info/top_level.txt
adafruit_circuitpython_vl53l1x-1.2.6.dist-info/RECORD
